setup.py
pip_abc.egg-info/PKG-INFO
pip_abc.egg-info/SOURCES.txt
pip_abc.egg-info/dependency_links.txt
pip_abc.egg-info/entry_points.txt
pip_abc.egg-info/not-zip-safe
pip_abc.egg-info/top_level.txt
pypidemo/__init__.py
pypidemo/cli.py